{
  "generated_at": "2026-07-19T04:10:03.696482",
  "reference_date": "2026-07-18",
  "actions": [
    {
      "type": "high_spending",
      "priority": "high",
      "title": "🔴 Ciccio + Sorriso ADV · spesa anomala alta",
      "platform": "Meta",
      "account_id": "421004342260012",
      "ad_url": "https://business.facebook.com/adsmanager/manage/campaigns?act=421004342260012",
      "details": "Spesa 294,71 € ieri vs media 7gg 196,71 € (+49,8%)",
      "reference_date": "2026-07-18",
      "reference_date_label": "18 lug 2026"
    },
    {
      "type": "high_spending",
      "priority": "high",
      "title": "🔴 Arianna Club Family · spesa anomala alta",
      "platform": "Google",
      "account_id": "752-894-5060",
      "ad_url": "https://ads.google.com/aw/campaigns?__c=7528945060",
      "details": "Spesa 51,08 € ieri vs media 7gg 0,49 € (+10328,6%)",
      "reference_date": "2026-07-18",
      "reference_date_label": "18 lug 2026"
    },
    {
      "type": "spending_anomaly",
      "priority": "high",
      "title": "Alert spending — 18/07/2026",
      "details": "1 zero + 11 high",
      "reference_date": "2026-07-18",
      "reference_date_label": "18 lug 2026",
      "slack_target": "C0B2RE5KSHG",
      "slack_template": ":rotating_light: *Check spending — 18/07/2026*\n*Top alert:*\n• :zap: ADS - Adèsso Hotel (Meta) — 0,00 € (storico 2,29 €) · _Causa da verificare_\n• :fire: Ciccio + Sorriso ADV (Meta) — 294,71 € (+49,8%)\n• :fire: Sardinia Family Villas (Google) — 95,95 € (+1,1%)\n_+ 9 altri alert sulla dashboard_\n\n<https://advfmosca.github.io/dashboard-di-controllo/?section=spending&date=2026-07-18|:link: Apri dashboard →>",
      "skip_if_quiet": false
    }
  ]
}