{"reference_date": "2026-07-10", "reference_date_label": "10 lug 2026", "generated_at": "2026-07-11T09:12:30.663895", "pages_url": "https://advfmosca.github.io/dashboard-di-controllo/", "overview": {"total_spend": 3208.37, "active_accounts": 55, "total_accounts": 60, "date_label": "10/07/2026", "platforms": [{"name": "Meta", "accounts": 39, "spend": 2556.4, "pct": 79.68}, {"name": "Google", "accounts": 16, "spend": 541.92, "pct": 16.89}, {"name": "TikTok", "accounts": 5, "spend": 110.05, "pct": 3.43}], "projects": [{"name": "BeeFamily", "spend": 1890.55, "accounts": 29, "pct": 51.91}, {"name": "AGHC", "spend": 460.58, "accounts": 19, "pct": 12.65}, {"name": "Med & Tech", "spend": 176.33, "accounts": 7, "pct": 4.84}, {"name": "CEA", "spend": 1114.57, "accounts": 43, "pct": 30.6}]}, "spending": {"zero": [], "zero_count": 0, "high_count": 14}, "beefamily": {"entries_count": 38, "alerts": 4, "kpi": {"actives": 29, "total": 38, "total_spend": 1890.55}}, "aghc": {"cards_count": 15, "alerts": 6, "kpi": {"actives": 14, "total": 15}}, "medtech": {"entries_count": 7, "alerts": 7, "kpi": {"actives": 7, "total": 7, "total_spend": 176.33, "total_lead": 15, "rosso": 5, "giallo": 2, "verde": 0, "nero": 0, "cpl_y": 11.76}, "_meta": {"reference_date": "2026-07-10", "semaphore_version": "v2", "source": "csv_alfredo", "synced_at": "2026-07-11T09:12:30.663895"}}, "cea": {"entries_count": 43, "alerts": 40, "kpi": {"actives": 43, "total": 43, "total_spend": 1114.57, "total_lead": 54, "rosso": 34, "giallo": 6, "verde": 3, "nero": 0, "cpl_y": 20.64}, "_meta": {"reference_date": "2026-07-10", "semaphore_version": "v2", "source": "csv_alfredo", "synced_at": "2026-07-11T09:12:30.663895"}}, "other_roster": {"total_count": 6, "total_spend_window": 1782.73}}